pyADA/__init__.py
pyADA/__main__.py
pyADA/pyADA.py
pyADAqsar-1.1.1.dist-info/LICENSE
pyADAqsar-1.1.1.dist-info/METADATA
pyADAqsar-1.1.1.dist-info/WHEEL
pyADAqsar-1.1.1.dist-info/top_level.txt
pyADAqsar-1.1.1.dist-info/RECORD
