Metadata-Version: 2.1
Name: pyADAqsar
Version: 1.1.1
Summary: A cheminformatics package to perform Applicability Domain of molecular fingerprints based in similarity calculation.
Home-page: https://github.com/jeffrichardchemistry/pyADA
Author: Jefferson Richard
Author-email: jrichardquimica@gmail.com
License: GNU GPL
Keywords: Cheminformatics,Chemistry,Applicability Domain,QSAR,SAR,Molecular Fingerprint
Classifier: Intended Audience :: Developers
Classifier: Intended Audience :: Science/Research
Classifier: Topic :: Scientific/Engineering :: Chemistry
Classifier: Topic :: Scientific/Engineering :: Physics
Classifier: Topic :: Scientific/Engineering :: Bio-Informatics
Classifier: Topic :: Scientific/Engineering
Classifier: License :: OSI Approved :: GNU General Public License v3 (GPLv3)
Classifier: Natural Language :: English
Classifier: Operating System :: Microsoft :: Windows
Classifier: Operating System :: POSIX :: Linux
Classifier: Environment :: MacOS X
Classifier: Programming Language :: Python :: 3.8
License-File: LICENSE
Requires-Dist: pandas <=2.0.3
Requires-Dist: scipy <=1.10.1
Requires-Dist: numpy <=1.24.4
Requires-Dist: tqdm
Requires-Dist: scikit-learn <=1.3.2
Requires-Dist: plotly
Provides-Extra: molplotly
Requires-Dist: molplotly ; extra == 'molplotly'
